{"accuracy": 0.15603216966594022, "rgb": "#ad5b00", "cb": 1, "words": [{"text": "run", "color": "#3e7409", "initloc": {"y": 0, "x": 0}, "size": 0.020504683256149292}, {"text": "taxi", "color": "#670a00", "initloc": {"y": 0, "x": 0}, "size": 0.020633768290281296}, {"text": "laps", "color": "#207e00", "initloc": {"y": 0, "x": 0}, "size": 0.02075384370982647}, {"text": "retirement", "color": "#aa3400", "initloc": {"y": 0, "x": 0}, "size": 0.021105535328388214}, {"text": "kicking", "color": "#a56e90", "initloc": {"y": 0, "x": 0}, "size": 0.021110018715262413}, {"text": "chase", "color": "#b6711f", "initloc": {"y": 0, "x": 0}, "size": 0.0213412307202816}, {"text": "ticket", "color": "#930000", "initloc": {"y": 0, "x": 0}, "size": 0.02135448157787323}, {"text": "kicked", "color": "#d0276d", "initloc": {"y": 0, "x": 0}, "size": 0.021661993116140366}, {"text": "bicycle", "color": "#00a600", "initloc": {"y": 0, "x": 0}, "size": 0.02168998122215271}, {"text": "ride", "color": "#292225", "initloc": {"y": 0, "x": 0}, "size": 0.022070102393627167}, {"text": "kick", "color": "#9e8480", "initloc": {"y": 0, "x": 0}, "size": 0.022430382668972015}, {"text": "truck", "color": "#418d00", "initloc": {"y": 0, "x": 0}, "size": 0.022577939555048943}, {"text": "wheelchair", "color": "#8b412d", "initloc": {"y": 0, "x": 0}, "size": 0.022666942328214645}, {"text": "car", "color": "#683b00", "initloc": {"y": 0, "x": 0}, "size": 0.022931991145014763}, {"text": "injured", "color": "#ff6a35", "initloc": {"y": 0, "x": 0}, "size": 0.023017508909106255}, {"text": "retire", "color": "#bf1c16", "initloc": {"y": 0, "x": 0}, "size": 0.02305600419640541}, {"text": "driver's", "color": "#8e4c00", "initloc": {"y": 0, "x": 0}, "size": 0.02357792668044567}, {"text": "bike", "color": "#0b7c0e", "initloc": {"y": 0, "x": 0}, "size": 0.02568560652434826}, {"text": "driver", "color": "#a05000", "initloc": {"y": 0, "x": 0}, "size": 0.026673508808016777}, {"text": "motorcycle", "color": "#42b200", "initloc": {"y": 0, "x": 0}, "size": 0.027304712682962418}], "ctm_idx": 146717, "freesurfer_idx": 272814, "hemi": "right"}