{"accuracy": 0.17506808045433733, "rgb": "#ccd165", "cb": 2, "words": [{"text": "kid", "color": "#f55084", "initloc": {"y": 0, "x": 0}, "size": 0.03231048211455345}, {"text": "asshole", "color": "#ff5cd3", "initloc": {"y": 0, "x": 0}, "size": 0.0323486402630806}, {"text": "laugh", "color": "#e626ff", "initloc": {"y": 0, "x": 0}, "size": 0.03235416114330292}, {"text": "embarrassed", "color": "#eb00df", "initloc": {"y": 0, "x": 0}, "size": 0.032411836087703705}, {"text": "girl's", "color": "#ec9379", "initloc": {"y": 0, "x": 0}, "size": 0.03273347392678261}, {"text": "boss", "color": "#e70e41", "initloc": {"y": 0, "x": 0}, "size": 0.03287603706121445}, {"text": "punch", "color": "#a7e3c5", "initloc": {"y": 0, "x": 0}, "size": 0.032940637320280075}, {"text": "cute", "color": "#c67dc9", "initloc": {"y": 0, "x": 0}, "size": 0.03312002867460251}, {"text": "yell", "color": "#ca3cca", "initloc": {"y": 0, "x": 0}, "size": 0.03327791020274162}, {"text": "upset", "color": "#ff00ef", "initloc": {"y": 0, "x": 0}, "size": 0.033443793654441833}, {"text": "sexy", "color": "#bbbfce", "initloc": {"y": 0, "x": 0}, "size": 0.03373515233397484}, {"text": "daddy", "color": "#e388bf", "initloc": {"y": 0, "x": 0}, "size": 0.033886224031448364}, {"text": "he'll", "color": "#ff36a1", "initloc": {"y": 0, "x": 0}, "size": 0.03412550315260887}, {"text": "girlfriend", "color": "#ff006b", "initloc": {"y": 0, "x": 0}, "size": 0.03419802710413933}, {"text": "hug", "color": "#c419ec", "initloc": {"y": 0, "x": 0}, "size": 0.03458791226148605}, {"text": "bitch", "color": "#ff78c2", "initloc": {"y": 0, "x": 0}, "size": 0.034966979175806046}, {"text": "kick", "color": "#9e8480", "initloc": {"y": 0, "x": 0}, "size": 0.03533681854605675}, {"text": "slap", "color": "#e9cdb8", "initloc": {"y": 0, "x": 0}, "size": 0.035748980939388275}, {"text": "boyfriend", "color": "#ff0079", "initloc": {"y": 0, "x": 0}, "size": 0.036281220614910126}, {"text": "dick", "color": "#ee9ccc", "initloc": {"y": 0, "x": 0}, "size": 0.03711116313934326}], "ctm_idx": 53398, "freesurfer_idx": 169476, "hemi": "right"}