{"accuracy": 0.004494223323317376, "rgb": "#8981ad", "cb": 0, "words": [{"text": "say", "color": "#ee29e4", "initloc": {"y": 0, "x": 0}, "size": 0.0071473754942417145}, {"text": "actually", "color": "#bb45e7", "initloc": {"y": 0, "x": 0}, "size": 0.0071689109317958355}, {"text": "funny", "color": "#eb46f9", "initloc": {"y": 0, "x": 0}, "size": 0.007170975208282471}, {"text": "bad", "color": "#f26bff", "initloc": {"y": 0, "x": 0}, "size": 0.007184722926467657}, {"text": "doesn't", "color": "#e374e8", "initloc": {"y": 0, "x": 0}, "size": 0.007188630755990744}, {"text": "yeah", "color": "#bd67d4", "initloc": {"y": 0, "x": 0}, "size": 0.0072052874602377415}, {"text": "silly", "color": "#c87aff", "initloc": {"y": 0, "x": 0}, "size": 0.007206166163086891}, {"text": "think", "color": "#db46ee", "initloc": {"y": 0, "x": 0}, "size": 0.007209142670035362}, {"text": "know", "color": "#ef1ad4", "initloc": {"y": 0, "x": 0}, "size": 0.007213464938104153}, {"text": "guess", "color": "#cd3fd1", "initloc": {"y": 0, "x": 0}, "size": 0.0072227222844958305}, {"text": "that's", "color": "#ca6fc3", "initloc": {"y": 0, "x": 0}, "size": 0.0072257076390087605}, {"text": "honestly", "color": "#d630ff", "initloc": {"y": 0, "x": 0}, "size": 0.007242781110107899}, {"text": "totally", "color": "#ca45fd", "initloc": {"y": 0, "x": 0}, "size": 0.007245116401463747}, {"text": "okay", "color": "#ef31e8", "initloc": {"y": 0, "x": 0}, "size": 0.007256024982780218}, {"text": "saying", "color": "#ff2fff", "initloc": {"y": 0, "x": 0}, "size": 0.007265444844961166}, {"text": "anything", "color": "#cc38d6", "initloc": {"y": 0, "x": 0}, "size": 0.007279139012098312}, {"text": "sure", "color": "#d92ec1", "initloc": {"y": 0, "x": 0}, "size": 0.00730486074462533}, {"text": "mean", "color": "#da6dff", "initloc": {"y": 0, "x": 0}, "size": 0.0073609608225524426}, {"text": "kind", "color": "#c363fc", "initloc": {"y": 0, "x": 0}, "size": 0.007362460717558861}, {"text": "seriously", "color": "#f24cf3", "initloc": {"y": 0, "x": 0}, "size": 0.007630297914147377}], "ctm_idx": 1737, "freesurfer_idx": 277486, "hemi": "right"}