{"accuracy": 0.02131223105774325, "rgb": "#6e988a", "cb": 1, "words": [{"text": "oil", "color": "#25ff67", "initloc": {"y": 0, "x": 0}, "size": 0.005381574854254723}, {"text": "rapidly", "color": "#07e791", "initloc": {"y": 0, "x": 0}, "size": 0.005402900278568268}, {"text": "approximately", "color": "#00db00", "initloc": {"y": 0, "x": 0}, "size": 0.00543319433927536}, {"text": "basin", "color": "#00ee2f", "initloc": {"y": 0, "x": 0}, "size": 0.005469008348882198}, {"text": "powder", "color": "#18ff82", "initloc": {"y": 0, "x": 0}, "size": 0.005479241721332073}, {"text": "producing", "color": "#00ff6c", "initloc": {"y": 0, "x": 0}, "size": 0.005535852629691362}, {"text": "liquid", "color": "#00ffaf", "initloc": {"y": 0, "x": 0}, "size": 0.0055653685703873634}, {"text": "copper", "color": "#00ff30", "initloc": {"y": 0, "x": 0}, "size": 0.005568148102611303}, {"text": "cement", "color": "#00ff63", "initloc": {"y": 0, "x": 0}, "size": 0.0055765425786376}, {"text": "cooling", "color": "#00f98a", "initloc": {"y": 0, "x": 0}, "size": 0.005578966345638037}, {"text": "produces", "color": "#00ff8c", "initloc": {"y": 0, "x": 0}, "size": 0.005604860372841358}, {"text": "salt", "color": "#09ff9d", "initloc": {"y": 0, "x": 0}, "size": 0.005655247718095779}, {"text": "surface", "color": "#00ff93", "initloc": {"y": 0, "x": 0}, "size": 0.005667767487466335}, {"text": "heat", "color": "#00ff96", "initloc": {"y": 0, "x": 0}, "size": 0.005682658404111862}, {"text": "plant", "color": "#0bff5a", "initloc": {"y": 0, "x": 0}, "size": 0.005682720802724361}, {"text": "mixture", "color": "#00ffbe", "initloc": {"y": 0, "x": 0}, "size": 0.005686083342880011}, {"text": "excess", "color": "#28ff4f", "initloc": {"y": 0, "x": 0}, "size": 0.005709972698241472}, {"text": "soil", "color": "#00ff86", "initloc": {"y": 0, "x": 0}, "size": 0.0057465266436338425}, {"text": "resulting", "color": "#3dff62", "initloc": {"y": 0, "x": 0}, "size": 0.005788241047412157}, {"text": "water", "color": "#00ff80", "initloc": {"y": 0, "x": 0}, "size": 0.006285882089287043}], "ctm_idx": 95955, "freesurfer_idx": 23322, "hemi": "left"}