{"accuracy": 0.010263195069475853, "rgb": "#878594", "cb": 0, "words": [{"text": "seriously", "color": "#f24cf3", "initloc": {"y": 0, "x": 0}, "size": 0.0036004476714879274}, {"text": "tough", "color": "#ba95ec", "initloc": {"y": 0, "x": 0}, "size": 0.003601353382691741}, {"text": "ass", "color": "#b4aea8", "initloc": {"y": 0, "x": 0}, "size": 0.0036234459839761257}, {"text": "badly", "color": "#ff30ff", "initloc": {"y": 0, "x": 0}, "size": 0.003631073050200939}, {"text": "trying", "color": "#bc37d5", "initloc": {"y": 0, "x": 0}, "size": 0.00363475875928998}, {"text": "pulling", "color": "#5dd087", "initloc": {"y": 0, "x": 0}, "size": 0.0036400097887963057}, {"text": "kicking", "color": "#a56e90", "initloc": {"y": 0, "x": 0}, "size": 0.003641429590061307}, {"text": "worse", "color": "#ff53ff", "initloc": {"y": 0, "x": 0}, "size": 0.003650033613666892}, {"text": "jump", "color": "#48898f", "initloc": {"y": 0, "x": 0}, "size": 0.0037186811678111553}, {"text": "pull", "color": "#5cd179", "initloc": {"y": 0, "x": 0}, "size": 0.0037703257985413074}, {"text": "slap", "color": "#e9cdb8", "initloc": {"y": 0, "x": 0}, "size": 0.003775217104703188}, {"text": "hurting", "color": "#f45bff", "initloc": {"y": 0, "x": 0}, "size": 0.0038155342917889357}, {"text": "push", "color": "#3cbfcd", "initloc": {"y": 0, "x": 0}, "size": 0.0038793839048594236}, {"text": "leg", "color": "#87fd3b", "initloc": {"y": 0, "x": 0}, "size": 0.0038901157677173615}, {"text": "fight", "color": "#ff66b7", "initloc": {"y": 0, "x": 0}, "size": 0.003902666736394167}, {"text": "stop", "color": "#d028d5", "initloc": {"y": 0, "x": 0}, "size": 0.003943206276744604}, {"text": "kill", "color": "#ff83e6", "initloc": {"y": 0, "x": 0}, "size": 0.00410506734624505}, {"text": "kick", "color": "#9e8480", "initloc": {"y": 0, "x": 0}, "size": 0.004257722292095423}, {"text": "lose", "color": "#d885b6", "initloc": {"y": 0, "x": 0}, "size": 0.0042883045971393585}, {"text": "hurt", "color": "#ff87ff", "initloc": {"y": 0, "x": 0}, "size": 0.004425236489623785}], "ctm_idx": 138889, "freesurfer_idx": 42907, "hemi": "left"}