{"accuracy": 0.012199767582669918, "rgb": "#96709a", "cb": 0, "words": [{"text": "mom", "color": "#ff006b", "initloc": {"y": 0, "x": 0}, "size": 0.008824929594993591}, {"text": "guy's", "color": "#ff7fa2", "initloc": {"y": 0, "x": 0}, "size": 0.008866706863045692}, {"text": "embarrassed", "color": "#eb00df", "initloc": {"y": 0, "x": 0}, "size": 0.008885364979505539}, {"text": "whore", "color": "#ff7bb6", "initloc": {"y": 0, "x": 0}, "size": 0.008909241296350956}, {"text": "laugh", "color": "#e626ff", "initloc": {"y": 0, "x": 0}, "size": 0.008912716992199421}, {"text": "sorry", "color": "#ff12ff", "initloc": {"y": 0, "x": 0}, "size": 0.008917931467294693}, {"text": "seriously", "color": "#f24cf3", "initloc": {"y": 0, "x": 0}, "size": 0.008920645341277122}, {"text": "he's", "color": "#ff59c3", "initloc": {"y": 0, "x": 0}, "size": 0.008933188393712044}, {"text": "fucked", "color": "#ff3dde", "initloc": {"y": 0, "x": 0}, "size": 0.009005595929920673}, {"text": "tell", "color": "#fe07cc", "initloc": {"y": 0, "x": 0}, "size": 0.009073317050933838}, {"text": "boyfriend", "color": "#ff0079", "initloc": {"y": 0, "x": 0}, "size": 0.009091752581298351}, {"text": "thinks", "color": "#ff40fa", "initloc": {"y": 0, "x": 0}, "size": 0.009104672819375992}, {"text": "girlfriend", "color": "#ff006b", "initloc": {"y": 0, "x": 0}, "size": 0.009127450175583363}, {"text": "asshole", "color": "#ff5cd3", "initloc": {"y": 0, "x": 0}, "size": 0.009178226813673973}, {"text": "ask", "color": "#f2008f", "initloc": {"y": 0, "x": 0}, "size": 0.00918617844581604}, {"text": "asking", "color": "#fe0097", "initloc": {"y": 0, "x": 0}, "size": 0.0092017175629735}, {"text": "okay", "color": "#ef31e8", "initloc": {"y": 0, "x": 0}, "size": 0.009201781824231148}, {"text": "bitch", "color": "#ff78c2", "initloc": {"y": 0, "x": 0}, "size": 0.00928453914821148}, {"text": "she's", "color": "#ff4fb1", "initloc": {"y": 0, "x": 0}, "size": 0.00933346338570118}, {"text": "telling", "color": "#ff00e2", "initloc": {"y": 0, "x": 0}, "size": 0.009502308443188667}], "ctm_idx": 3752, "freesurfer_idx": 255997, "hemi": "right"}