{"accuracy": 0.03014630942683688, "rgb": "#7c728d", "cb": 0, "words": [{"text": "houses", "color": "#005700", "initloc": {"y": 0, "x": 0}, "size": 0.0024655151646584272}, {"text": "workers", "color": "#6e8700", "initloc": {"y": 0, "x": 0}, "size": 0.002476207911968231}, {"text": "settlers", "color": "#908047", "initloc": {"y": 0, "x": 0}, "size": 0.0025094046723097563}, {"text": "property", "color": "#c44f00", "initloc": {"y": 0, "x": 0}, "size": 0.0025124764069914818}, {"text": "factories", "color": "#21cd2c", "initloc": {"y": 0, "x": 0}, "size": 0.002514780731871724}, {"text": "industrial", "color": "#00ee58", "initloc": {"y": 0, "x": 0}, "size": 0.0025322637520730495}, {"text": "offices", "color": "#253e00", "initloc": {"y": 0, "x": 0}, "size": 0.0025614933110773563}, {"text": "activities", "color": "#213123", "initloc": {"y": 0, "x": 0}, "size": 0.002606387250125408}, {"text": "establishment", "color": "#8f5255", "initloc": {"y": 0, "x": 0}, "size": 0.002610074356198311}, {"text": "estate", "color": "#8f4c00", "initloc": {"y": 0, "x": 0}, "size": 0.0026447558775544167}, {"text": "commerce", "color": "#5a7e2f", "initloc": {"y": 0, "x": 0}, "size": 0.0027488309424370527}, {"text": "merchants", "color": "#5e950f", "initloc": {"y": 0, "x": 0}, "size": 0.0027798046357929707}, {"text": "grounds", "color": "#7b1f25", "initloc": {"y": 0, "x": 0}, "size": 0.0027844272553920746}, {"text": "community", "color": "#4d1658", "initloc": {"y": 0, "x": 0}, "size": 0.0028268923051655293}, {"text": "farm", "color": "#5f8800", "initloc": {"y": 0, "x": 0}, "size": 0.0028587402775883675}, {"text": "residents", "color": "#324000", "initloc": {"y": 0, "x": 0}, "size": 0.0028827551286667585}, {"text": "premises", "color": "#97070e", "initloc": {"y": 0, "x": 0}, "size": 0.0029439209029078484}, {"text": "homes", "color": "#502900", "initloc": {"y": 0, "x": 0}, "size": 0.002955561736598611}, {"text": "farms", "color": "#33b71d", "initloc": {"y": 0, "x": 0}, "size": 0.0030280500650405884}, {"text": "farmers", "color": "#54bd24", "initloc": {"y": 0, "x": 0}, "size": 0.003369735088199377}], "ctm_idx": 157837, "freesurfer_idx": 7513, "hemi": "left"}