{"accuracy": 0.09407952658190576, "rgb": "#86754c", "cb": 1, "words": [{"text": "vehicle", "color": "#2ca400", "initloc": {"y": 0, "x": 0}, "size": 0.010403448715806007}, {"text": "brakes", "color": "#37b24b", "initloc": {"y": 0, "x": 0}, "size": 0.010500406846404076}, {"text": "drove", "color": "#7f0016", "initloc": {"y": 0, "x": 0}, "size": 0.010540064424276352}, {"text": "ride", "color": "#292225", "initloc": {"y": 0, "x": 0}, "size": 0.010547967627644539}, {"text": "riding", "color": "#3a9e3c", "initloc": {"y": 0, "x": 0}, "size": 0.010548820719122887}, {"text": "cars", "color": "#008b00", "initloc": {"y": 0, "x": 0}, "size": 0.010643220506608486}, {"text": "injured", "color": "#ff6a35", "initloc": {"y": 0, "x": 0}, "size": 0.010708015412092209}, {"text": "drive", "color": "#1c1c00", "initloc": {"y": 0, "x": 0}, "size": 0.010793018154799938}, {"text": "runs", "color": "#299500", "initloc": {"y": 0, "x": 0}, "size": 0.010832141153514385}, {"text": "run", "color": "#3e7409", "initloc": {"y": 0, "x": 0}, "size": 0.010897628031671047}, {"text": "driving", "color": "#6f123c", "initloc": {"y": 0, "x": 0}, "size": 0.010974523611366749}, {"text": "laps", "color": "#207e00", "initloc": {"y": 0, "x": 0}, "size": 0.0109917763620615}, {"text": "chase", "color": "#b6711f", "initloc": {"y": 0, "x": 0}, "size": 0.011035230942070484}, {"text": "racing", "color": "#0ba500", "initloc": {"y": 0, "x": 0}, "size": 0.01156003586947918}, {"text": "bicycle", "color": "#00a600", "initloc": {"y": 0, "x": 0}, "size": 0.011632375419139862}, {"text": "car", "color": "#683b00", "initloc": {"y": 0, "x": 0}, "size": 0.012049246579408646}, {"text": "truck", "color": "#418d00", "initloc": {"y": 0, "x": 0}, "size": 0.012323585338890553}, {"text": "driver", "color": "#a05000", "initloc": {"y": 0, "x": 0}, "size": 0.012700820341706276}, {"text": "bike", "color": "#0b7c0e", "initloc": {"y": 0, "x": 0}, "size": 0.012964596971869469}, {"text": "motorcycle", "color": "#42b200", "initloc": {"y": 0, "x": 0}, "size": 0.014526027254760265}], "ctm_idx": 144342, "freesurfer_idx": 52412, "hemi": "left"}