{"accuracy": 0.023195574165905015, "rgb": "#757794", "cb": 0, "words": [{"text": "north", "color": "#09a008", "initloc": {"y": 0, "x": 0}, "size": 0.004400840029120445}, {"text": "walls", "color": "#00cb71", "initloc": {"y": 0, "x": 0}, "size": 0.004407250322401524}, {"text": "exterior", "color": "#00f839", "initloc": {"y": 0, "x": 0}, "size": 0.004431803245097399}, {"text": "area", "color": "#00a800", "initloc": {"y": 0, "x": 0}, "size": 0.004456996452063322}, {"text": "upper", "color": "#00ff1c", "initloc": {"y": 0, "x": 0}, "size": 0.004460500553250313}, {"text": "granite", "color": "#00ff29", "initloc": {"y": 0, "x": 0}, "size": 0.004460756666958332}, {"text": "metres", "color": "#00e206", "initloc": {"y": 0, "x": 0}, "size": 0.004517511464655399}, {"text": "tower", "color": "#007c39", "initloc": {"y": 0, "x": 0}, "size": 0.004549538716673851}, {"text": "surrounding", "color": "#00cb70", "initloc": {"y": 0, "x": 0}, "size": 0.004553073085844517}, {"text": "constructed", "color": "#00b41d", "initloc": {"y": 0, "x": 0}, "size": 0.004559407010674477}, {"text": "dome", "color": "#00f53c", "initloc": {"y": 0, "x": 0}, "size": 0.004562886897474527}, {"text": "sea", "color": "#12c161", "initloc": {"y": 0, "x": 0}, "size": 0.0045884703285992146}, {"text": "basin", "color": "#00ee2f", "initloc": {"y": 0, "x": 0}, "size": 0.004610537551343441}, {"text": "remains", "color": "#68a64d", "initloc": {"y": 0, "x": 0}, "size": 0.004620952066034079}, {"text": "ocean", "color": "#00af8e", "initloc": {"y": 0, "x": 0}, "size": 0.004660226404666901}, {"text": "entrance", "color": "#004300", "initloc": {"y": 0, "x": 0}, "size": 0.004684000741690397}, {"text": "situated", "color": "#009e00", "initloc": {"y": 0, "x": 0}, "size": 0.004685274325311184}, {"text": "chamber", "color": "#1cac55", "initloc": {"y": 0, "x": 0}, "size": 0.004721820820122957}, {"text": "located", "color": "#00a200", "initloc": {"y": 0, "x": 0}, "size": 0.004728294909000397}, {"text": "interior", "color": "#00dc24", "initloc": {"y": 0, "x": 0}, "size": 0.0050069186836481094}], "ctm_idx": 49908, "freesurfer_idx": 318651, "hemi": "right"}