{"accuracy": 0.031284972215600886, "rgb": "#6c6676", "cb": 1, "words": [{"text": "mountain", "color": "#00e23d", "initloc": {"y": 0, "x": 0}, "size": 0.006975532043725252}, {"text": "ridge", "color": "#00da3d", "initloc": {"y": 0, "x": 0}, "size": 0.0069796135649085045}, {"text": "plaza", "color": "#006900", "initloc": {"y": 0, "x": 0}, "size": 0.007010426372289658}, {"text": "mount", "color": "#11c423", "initloc": {"y": 0, "x": 0}, "size": 0.007040327414870262}, {"text": "located", "color": "#00a200", "initloc": {"y": 0, "x": 0}, "size": 0.0070458464324474335}, {"text": "near", "color": "#1f6e14", "initloc": {"y": 0, "x": 0}, "size": 0.0070516387932002544}, {"text": "hillside", "color": "#009522", "initloc": {"y": 0, "x": 0}, "size": 0.007071444299072027}, {"text": "road", "color": "#006600", "initloc": {"y": 0, "x": 0}, "size": 0.0070938970893621445}, {"text": "corner", "color": "#009d18", "initloc": {"y": 0, "x": 0}, "size": 0.007099855691194534}, {"text": "nearby", "color": "#175c00", "initloc": {"y": 0, "x": 0}, "size": 0.007115107960999012}, {"text": "hall", "color": "#113a00", "initloc": {"y": 0, "x": 0}, "size": 0.007131507620215416}, {"text": "hills", "color": "#00b93a", "initloc": {"y": 0, "x": 0}, "size": 0.007164849899709225}, {"text": "closed", "color": "#001625", "initloc": {"y": 0, "x": 0}, "size": 0.007166914641857147}, {"text": "valley", "color": "#00c138", "initloc": {"y": 0, "x": 0}, "size": 0.007185111753642559}, {"text": "tower", "color": "#007c39", "initloc": {"y": 0, "x": 0}, "size": 0.007221105974167585}, {"text": "sits", "color": "#0e7e1a", "initloc": {"y": 0, "x": 0}, "size": 0.007249247748404741}, {"text": "terrace", "color": "#007a03", "initloc": {"y": 0, "x": 0}, "size": 0.007350108586251736}, {"text": "opened", "color": "#093005", "initloc": {"y": 0, "x": 0}, "size": 0.007498660124838352}, {"text": "hill", "color": "#02be2c", "initloc": {"y": 0, "x": 0}, "size": 0.007554263342171907}, {"text": "station", "color": "#005a00", "initloc": {"y": 0, "x": 0}, "size": 0.0079287588596344}], "ctm_idx": 120365, "freesurfer_idx": 170233, "hemi": "right"}