{"accuracy": 0.027042129631250116, "rgb": "#7f7c7d", "cb": 0, "words": [{"text": "remove", "color": "#8dfd85", "initloc": {"y": 0, "x": 0}, "size": 0.002154239919036627}, {"text": "pulling", "color": "#5dd087", "initloc": {"y": 0, "x": 0}, "size": 0.00215593702159822}, {"text": "neck", "color": "#5cff82", "initloc": {"y": 0, "x": 0}, "size": 0.0021660765632987022}, {"text": "handle", "color": "#92a297", "initloc": {"y": 0, "x": 0}, "size": 0.002166494494304061}, {"text": "shoulder", "color": "#64e478", "initloc": {"y": 0, "x": 0}, "size": 0.0021978968288749456}, {"text": "prevent", "color": "#b8dda5", "initloc": {"y": 0, "x": 0}, "size": 0.002213719766587019}, {"text": "lift", "color": "#00e264", "initloc": {"y": 0, "x": 0}, "size": 0.0022160629741847515}, {"text": "weight", "color": "#42ff92", "initloc": {"y": 0, "x": 0}, "size": 0.0022346351761370897}, {"text": "holster", "color": "#79e647", "initloc": {"y": 0, "x": 0}, "size": 0.00225732009857893}, {"text": "legs", "color": "#4cff65", "initloc": {"y": 0, "x": 0}, "size": 0.002285450929775834}, {"text": "safety", "color": "#929a31", "initloc": {"y": 0, "x": 0}, "size": 0.0022979872301220894}, {"text": "gun", "color": "#cbc45e", "initloc": {"y": 0, "x": 0}, "size": 0.002325800945982337}, {"text": "wrist", "color": "#88ff72", "initloc": {"y": 0, "x": 0}, "size": 0.002338351681828499}, {"text": "strap", "color": "#38ff2f", "initloc": {"y": 0, "x": 0}, "size": 0.0023543310817331076}, {"text": "foot", "color": "#29f82e", "initloc": {"y": 0, "x": 0}, "size": 0.0024179010652005672}, {"text": "drop", "color": "#47d145", "initloc": {"y": 0, "x": 0}, "size": 0.002442748751491308}, {"text": "pull", "color": "#5cd179", "initloc": {"y": 0, "x": 0}, "size": 0.002459154464304447}, {"text": "arm", "color": "#7eff7b", "initloc": {"y": 0, "x": 0}, "size": 0.0024713329039514065}, {"text": "carry", "color": "#a1da45", "initloc": {"y": 0, "x": 0}, "size": 0.002511408179998398}, {"text": "leg", "color": "#87fd3b", "initloc": {"y": 0, "x": 0}, "size": 0.00268193194642663}], "ctm_idx": 76244, "freesurfer_idx": 44914, "hemi": "left"}