{"accuracy": 0.10761884231088169, "rgb": "#79ffc1", "cb": 2, "words": [{"text": "ink", "color": "#2eff60", "initloc": {"y": 0, "x": 0}, "size": 0.02474028430879116}, {"text": "process", "color": "#52bdbe", "initloc": {"y": 0, "x": 0}, "size": 0.024762213230133057}, {"text": "removing", "color": "#82ffaa", "initloc": {"y": 0, "x": 0}, "size": 0.024802938103675842}, {"text": "contents", "color": "#479f46", "initloc": {"y": 0, "x": 0}, "size": 0.024846820160746574}, {"text": "inserted", "color": "#74ff68", "initloc": {"y": 0, "x": 0}, "size": 0.024980049580335617}, {"text": "technique", "color": "#00ffd0", "initloc": {"y": 0, "x": 0}, "size": 0.025121914222836494}, {"text": "items", "color": "#25cc00", "initloc": {"y": 0, "x": 0}, "size": 0.025346575304865837}, {"text": "x", "color": "#1bce37", "initloc": {"y": 0, "x": 0}, "size": 0.025953741744160652}, {"text": "extract", "color": "#40ffb7", "initloc": {"y": 0, "x": 0}, "size": 0.026253284886479378}, {"text": "attach", "color": "#4cff5d", "initloc": {"y": 0, "x": 0}, "size": 0.026258083060383797}, {"text": "remove", "color": "#8dfd85", "initloc": {"y": 0, "x": 0}, "size": 0.026583455502986908}, {"text": "use", "color": "#3fd385", "initloc": {"y": 0, "x": 0}, "size": 0.027234245091676712}, {"text": "type", "color": "#51ffa4", "initloc": {"y": 0, "x": 0}, "size": 0.02733594737946987}, {"text": "replace", "color": "#49ee5c", "initloc": {"y": 0, "x": 0}, "size": 0.027806058526039124}, {"text": "item", "color": "#5ccc00", "initloc": {"y": 0, "x": 0}, "size": 0.028625763952732086}, {"text": "add", "color": "#3fdf9b", "initloc": {"y": 0, "x": 0}, "size": 0.02878553792834282}, {"text": "method", "color": "#2fe7a8", "initloc": {"y": 0, "x": 0}, "size": 0.028934676200151443}, {"text": "uses", "color": "#48ff9f", "initloc": {"y": 0, "x": 0}, "size": 0.03006482869386673}, {"text": "using", "color": "#2de8a1", "initloc": {"y": 0, "x": 0}, "size": 0.030433963984251022}, {"text": "adding", "color": "#18efbf", "initloc": {"y": 0, "x": 0}, "size": 0.03090137243270874}], "ctm_idx": 35466, "freesurfer_idx": 46380, "hemi": "left"}