{"accuracy": 0.04653466170161717, "rgb": "#60919d", "cb": 1, "words": [{"text": "bay", "color": "#009121", "initloc": {"y": 0, "x": 0}, "size": 0.009328912012279034}, {"text": "canyon", "color": "#00d03f", "initloc": {"y": 0, "x": 0}, "size": 0.009360943920910358}, {"text": "rocky", "color": "#06da68", "initloc": {"y": 0, "x": 0}, "size": 0.00945071130990982}, {"text": "mount", "color": "#11c423", "initloc": {"y": 0, "x": 0}, "size": 0.009470654651522636}, {"text": "sea", "color": "#12c161", "initloc": {"y": 0, "x": 0}, "size": 0.009475975297391415}, {"text": "creek", "color": "#04eb39", "initloc": {"y": 0, "x": 0}, "size": 0.009485290385782719}, {"text": "north", "color": "#09a008", "initloc": {"y": 0, "x": 0}, "size": 0.009588361717760563}, {"text": "cliffs", "color": "#00d86a", "initloc": {"y": 0, "x": 0}, "size": 0.0095957787707448}, {"text": "hill", "color": "#02be2c", "initloc": {"y": 0, "x": 0}, "size": 0.009705730713903904}, {"text": "pine", "color": "#00ff53", "initloc": {"y": 0, "x": 0}, "size": 0.009714111685752869}, {"text": "ridge", "color": "#00da3d", "initloc": {"y": 0, "x": 0}, "size": 0.00974110048264265}, {"text": "mountains", "color": "#00bb5d", "initloc": {"y": 0, "x": 0}, "size": 0.009872714057564735}, {"text": "hills", "color": "#00b93a", "initloc": {"y": 0, "x": 0}, "size": 0.009873002767562866}, {"text": "valley", "color": "#00c138", "initloc": {"y": 0, "x": 0}, "size": 0.009907959029078484}, {"text": "river", "color": "#03d229", "initloc": {"y": 0, "x": 0}, "size": 0.009927930310368538}, {"text": "slopes", "color": "#00f449", "initloc": {"y": 0, "x": 0}, "size": 0.009941872209310532}, {"text": "forest", "color": "#02c458", "initloc": {"y": 0, "x": 0}, "size": 0.010179425589740276}, {"text": "spring", "color": "#00e313", "initloc": {"y": 0, "x": 0}, "size": 0.010208100080490112}, {"text": "lake", "color": "#00d43c", "initloc": {"y": 0, "x": 0}, "size": 0.010264845564961433}, {"text": "mountain", "color": "#00e23d", "initloc": {"y": 0, "x": 0}, "size": 0.010745461098849773}], "ctm_idx": 44094, "freesurfer_idx": 301355, "hemi": "right"}