{"accuracy": 0.09356648589018939, "rgb": "#a06699", "cb": 1, "words": [{"text": "convince", "color": "#ff09e8", "initloc": {"y": 0, "x": 0}, "size": 0.016684599220752716}, {"text": "submit", "color": "#e5288a", "initloc": {"y": 0, "x": 0}, "size": 0.0168075580149889}, {"text": "yell", "color": "#ca3cca", "initloc": {"y": 0, "x": 0}, "size": 0.01681656204164028}, {"text": "answering", "color": "#d100ca", "initloc": {"y": 0, "x": 0}, "size": 0.016872243955731392}, {"text": "asshole", "color": "#ff5cd3", "initloc": {"y": 0, "x": 0}, "size": 0.016917448490858078}, {"text": "quit", "color": "#b906bb", "initloc": {"y": 0, "x": 0}, "size": 0.016965337097644806}, {"text": "nerd", "color": "#9a73d7", "initloc": {"y": 0, "x": 0}, "size": 0.017001960426568985}, {"text": "reply", "color": "#ff00dd", "initloc": {"y": 0, "x": 0}, "size": 0.017041422426700592}, {"text": "smart", "color": "#d169c3", "initloc": {"y": 0, "x": 0}, "size": 0.017081089317798615}, {"text": "rage", "color": "#df42ff", "initloc": {"y": 0, "x": 0}, "size": 0.017330925911664963}, {"text": "disappointed", "color": "#d300ff", "initloc": {"y": 0, "x": 0}, "size": 0.017440108582377434}, {"text": "upset", "color": "#ff00ef", "initloc": {"y": 0, "x": 0}, "size": 0.017466358840465546}, {"text": "annoyed", "color": "#df00f4", "initloc": {"y": 0, "x": 0}, "size": 0.017474813386797905}, {"text": "idiot", "color": "#ff60e7", "initloc": {"y": 0, "x": 0}, "size": 0.01760455220937729}, {"text": "whoever", "color": "#ff40be", "initloc": {"y": 0, "x": 0}, "size": 0.017682036384940147}, {"text": "pissed", "color": "#f40caa", "initloc": {"y": 0, "x": 0}, "size": 0.017725646495819092}, {"text": "he'll", "color": "#ff36a1", "initloc": {"y": 0, "x": 0}, "size": 0.01778557524085045}, {"text": "click", "color": "#763cb6", "initloc": {"y": 0, "x": 0}, "size": 0.017916975542902946}, {"text": "boss", "color": "#e70e41", "initloc": {"y": 0, "x": 0}, "size": 0.017993247136473656}, {"text": "would've", "color": "#ff3fcc", "initloc": {"y": 0, "x": 0}, "size": 0.018467430025339127}], "ctm_idx": 116922, "freesurfer_idx": 297627, "hemi": "right"}