{"accuracy": 0.13160532023957786, "rgb": "#79bd82", "cb": 2, "words": [{"text": "drop", "color": "#47d145", "initloc": {"y": 0, "x": 0}, "size": 0.013234041631221771}, {"text": "beat", "color": "#ac8199", "initloc": {"y": 0, "x": 0}, "size": 0.013270138762891293}, {"text": "bounced", "color": "#65a926", "initloc": {"y": 0, "x": 0}, "size": 0.013378188945353031}, {"text": "pull", "color": "#5cd179", "initloc": {"y": 0, "x": 0}, "size": 0.01347997598350048}, {"text": "ball", "color": "#18ff18", "initloc": {"y": 0, "x": 0}, "size": 0.013649476692080498}, {"text": "smash", "color": "#5de9ac", "initloc": {"y": 0, "x": 0}, "size": 0.013666659593582153}, {"text": "jumps", "color": "#758488", "initloc": {"y": 0, "x": 0}, "size": 0.013833526521921158}, {"text": "slam", "color": "#83b436", "initloc": {"y": 0, "x": 0}, "size": 0.013898925855755806}, {"text": "grab", "color": "#45aa54", "initloc": {"y": 0, "x": 0}, "size": 0.013927641324698925}, {"text": "throw", "color": "#80d076", "initloc": {"y": 0, "x": 0}, "size": 0.014086426235735416}, {"text": "kicked", "color": "#d0276d", "initloc": {"y": 0, "x": 0}, "size": 0.01411085668951273}, {"text": "knee", "color": "#6af477", "initloc": {"y": 0, "x": 0}, "size": 0.014249691739678383}, {"text": "hitting", "color": "#86a288", "initloc": {"y": 0, "x": 0}, "size": 0.014429491944611073}, {"text": "leg", "color": "#87fd3b", "initloc": {"y": 0, "x": 0}, "size": 0.014828835614025593}, {"text": "run", "color": "#3e7409", "initloc": {"y": 0, "x": 0}, "size": 0.014979316852986813}, {"text": "ankle", "color": "#70dd47", "initloc": {"y": 0, "x": 0}, "size": 0.015116793103516102}, {"text": "kicking", "color": "#a56e90", "initloc": {"y": 0, "x": 0}, "size": 0.015155491419136524}, {"text": "jumping", "color": "#6394b0", "initloc": {"y": 0, "x": 0}, "size": 0.015530196949839592}, {"text": "jump", "color": "#48898f", "initloc": {"y": 0, "x": 0}, "size": 0.01674075424671173}, {"text": "kick", "color": "#9e8480", "initloc": {"y": 0, "x": 0}, "size": 0.017996177077293396}], "ctm_idx": 90195, "freesurfer_idx": 228652, "hemi": "right"}