{"accuracy": 0.09143321128574669, "rgb": "#8e50bf", "cb": 1, "words": [{"text": "rude", "color": "#fb14e8", "initloc": {"y": 0, "x": 0}, "size": 0.013267723843455315}, {"text": "topic", "color": "#b218ff", "initloc": {"y": 0, "x": 0}, "size": 0.01328838337212801}, {"text": "reply", "color": "#ff00dd", "initloc": {"y": 0, "x": 0}, "size": 0.013313883915543556}, {"text": "talked", "color": "#ff00cc", "initloc": {"y": 0, "x": 0}, "size": 0.013358114287257195}, {"text": "thoughtful", "color": "#ce2dff", "initloc": {"y": 0, "x": 0}, "size": 0.013362554833292961}, {"text": "affection", "color": "#ff34ee", "initloc": {"y": 0, "x": 0}, "size": 0.013409999199211597}, {"text": "respectful", "color": "#f800e3", "initloc": {"y": 0, "x": 0}, "size": 0.013629676774144173}, {"text": "lesbian", "color": "#ff4b90", "initloc": {"y": 0, "x": 0}, "size": 0.013643168844282627}, {"text": "apologize", "color": "#ff00f7", "initloc": {"y": 0, "x": 0}, "size": 0.01381705328822136}, {"text": "gay", "color": "#ff50c5", "initloc": {"y": 0, "x": 0}, "size": 0.013983029872179031}, {"text": "polite", "color": "#e600d2", "initloc": {"y": 0, "x": 0}, "size": 0.01403583399951458}, {"text": "feelings", "color": "#ff00ff", "initloc": {"y": 0, "x": 0}, "size": 0.014117084443569183}, {"text": "offended", "color": "#ff36ff", "initloc": {"y": 0, "x": 0}, "size": 0.014143964275717735}, {"text": "talk", "color": "#e400e2", "initloc": {"y": 0, "x": 0}, "size": 0.014184382744133472}, {"text": "conversation", "color": "#c900c4", "initloc": {"y": 0, "x": 0}, "size": 0.01422283984720707}, {"text": "speaking", "color": "#f400ff", "initloc": {"y": 0, "x": 0}, "size": 0.014264740981161594}, {"text": "sincere", "color": "#ee21ff", "initloc": {"y": 0, "x": 0}, "size": 0.014325791969895363}, {"text": "loving", "color": "#ff40ff", "initloc": {"y": 0, "x": 0}, "size": 0.014486527070403099}, {"text": "conversations", "color": "#a600d5", "initloc": {"y": 0, "x": 0}, "size": 0.014705000445246696}, {"text": "speak", "color": "#ff00ff", "initloc": {"y": 0, "x": 0}, "size": 0.01551019586622715}], "ctm_idx": 46295, "freesurfer_idx": 174426, "hemi": "right"}