{"accuracy": 0.07129949876056538, "rgb": "#78b169", "cb": 0, "words": [{"text": "tied", "color": "#52f600", "initloc": {"y": 0, "x": 0}, "size": 0.008229240775108337}, {"text": "wrist", "color": "#88ff72", "initloc": {"y": 0, "x": 0}, "size": 0.008245415985584259}, {"text": "elbow", "color": "#51ff7f", "initloc": {"y": 0, "x": 0}, "size": 0.008340450935065746}, {"text": "dive", "color": "#05775f", "initloc": {"y": 0, "x": 0}, "size": 0.008341065607964993}, {"text": "player", "color": "#55ce00", "initloc": {"y": 0, "x": 0}, "size": 0.008353469893336296}, {"text": "glove", "color": "#75ff1e", "initloc": {"y": 0, "x": 0}, "size": 0.008372764103114605}, {"text": "opponent", "color": "#c3e17d", "initloc": {"y": 0, "x": 0}, "size": 0.00842239335179329}, {"text": "lift", "color": "#00e264", "initloc": {"y": 0, "x": 0}, "size": 0.008432365953922272}, {"text": "diving", "color": "#00c237", "initloc": {"y": 0, "x": 0}, "size": 0.008631967008113861}, {"text": "kick", "color": "#9e8480", "initloc": {"y": 0, "x": 0}, "size": 0.008639892563223839}, {"text": "heel", "color": "#4eff7f", "initloc": {"y": 0, "x": 0}, "size": 0.008649882860481739}, {"text": "tie", "color": "#15ff00", "initloc": {"y": 0, "x": 0}, "size": 0.008666088804602623}, {"text": "knee", "color": "#6af477", "initloc": {"y": 0, "x": 0}, "size": 0.00873088464140892}, {"text": "ropes", "color": "#09f446", "initloc": {"y": 0, "x": 0}, "size": 0.008788490667939186}, {"text": "lever", "color": "#0fff4b", "initloc": {"y": 0, "x": 0}, "size": 0.009230543859302998}, {"text": "ankle", "color": "#70dd47", "initloc": {"y": 0, "x": 0}, "size": 0.009286385960876942}, {"text": "jump", "color": "#48898f", "initloc": {"y": 0, "x": 0}, "size": 0.009309801273047924}, {"text": "strap", "color": "#38ff2f", "initloc": {"y": 0, "x": 0}, "size": 0.009369424544274807}, {"text": "ball", "color": "#18ff18", "initloc": {"y": 0, "x": 0}, "size": 0.009376546368002892}, {"text": "leg", "color": "#87fd3b", "initloc": {"y": 0, "x": 0}, "size": 0.010050392709672451}], "ctm_idx": 150068, "freesurfer_idx": 297012, "hemi": "right"}