{"accuracy": 0.0445301183517464, "rgb": "#778c7b", "cb": 0, "words": [{"text": "managed", "color": "#7e4123", "initloc": {"y": 0, "x": 0}, "size": 0.003741184249520302}, {"text": "round", "color": "#00e000", "initloc": {"y": 0, "x": 0}, "size": 0.003770700888708234}, {"text": "sturdy", "color": "#00ff62", "initloc": {"y": 0, "x": 0}, "size": 0.0037739186082035303}, {"text": "mantle's", "color": "#49d900", "initloc": {"y": 0, "x": 0}, "size": 0.0037775032687932253}, {"text": "mcgough", "color": "#40f113", "initloc": {"y": 0, "x": 0}, "size": 0.0037921122275292873}, {"text": "tartabull", "color": "#3de608", "initloc": {"y": 0, "x": 0}, "size": 0.0037925306241959333}, {"text": "lothario", "color": "#75d60c", "initloc": {"y": 0, "x": 0}, "size": 0.003864019177854061}, {"text": "tied", "color": "#52f600", "initloc": {"y": 0, "x": 0}, "size": 0.003864151891320944}, {"text": "steel", "color": "#00ff39", "initloc": {"y": 0, "x": 0}, "size": 0.003949057776480913}, {"text": "cutter", "color": "#51ff43", "initloc": {"y": 0, "x": 0}, "size": 0.0039677489548921585}, {"text": "steinbrenner", "color": "#66be00", "initloc": {"y": 0, "x": 0}, "size": 0.0040212105959653854}, {"text": "secured", "color": "#699300", "initloc": {"y": 0, "x": 0}, "size": 0.0040716007351875305}, {"text": "foot", "color": "#29f82e", "initloc": {"y": 0, "x": 0}, "size": 0.004083418287336826}, {"text": "pound", "color": "#67ff23", "initloc": {"y": 0, "x": 0}, "size": 0.004086044151335955}, {"text": "placed", "color": "#48e600", "initloc": {"y": 0, "x": 0}, "size": 0.004202661570161581}, {"text": "ball", "color": "#18ff18", "initloc": {"y": 0, "x": 0}, "size": 0.0042750034481287}, {"text": "mattingly", "color": "#81d000", "initloc": {"y": 0, "x": 0}, "size": 0.004285907838493586}, {"text": "leg", "color": "#87fd3b", "initloc": {"y": 0, "x": 0}, "size": 0.004333747085183859}, {"text": "replaced", "color": "#33ff00", "initloc": {"y": 0, "x": 0}, "size": 0.004396187607198954}, {"text": "needed", "color": "#408f00", "initloc": {"y": 0, "x": 0}, "size": 0.004568133503198624}], "ctm_idx": 85161, "freesurfer_idx": 219623, "hemi": "right"}