{"accuracy": 0.05430317572481843, "rgb": "#42a3a4", "cb": 1, "words": [{"text": "bloom", "color": "#0ed891", "initloc": {"y": 0, "x": 0}, "size": 0.015764689072966576}, {"text": "formation", "color": "#00f667", "initloc": {"y": 0, "x": 0}, "size": 0.015838932245969772}, {"text": "within", "color": "#28610d", "initloc": {"y": 0, "x": 0}, "size": 0.01594337821006775}, {"text": "forms", "color": "#0eff8d", "initloc": {"y": 0, "x": 0}, "size": 0.01595272123813629}, {"text": "central", "color": "#00a61e", "initloc": {"y": 0, "x": 0}, "size": 0.015968799591064453}, {"text": "diameter", "color": "#00ff40", "initloc": {"y": 0, "x": 0}, "size": 0.015974314883351326}, {"text": "formed", "color": "#10ed49", "initloc": {"y": 0, "x": 0}, "size": 0.016000811010599136}, {"text": "domes", "color": "#00f746", "initloc": {"y": 0, "x": 0}, "size": 0.01611142046749592}, {"text": "various", "color": "#00cb0d", "initloc": {"y": 0, "x": 0}, "size": 0.016137467697262764}, {"text": "form", "color": "#2dff72", "initloc": {"y": 0, "x": 0}, "size": 0.016148744150996208}, {"text": "composed", "color": "#27ff81", "initloc": {"y": 0, "x": 0}, "size": 0.016169611364603043}, {"text": "surrounding", "color": "#00cb70", "initloc": {"y": 0, "x": 0}, "size": 0.016282862052321434}, {"text": "originally", "color": "#31da2a", "initloc": {"y": 0, "x": 0}, "size": 0.01630392298102379}, {"text": "produced", "color": "#13ff43", "initloc": {"y": 0, "x": 0}, "size": 0.016413182020187378}, {"text": "addition", "color": "#00e100", "initloc": {"y": 0, "x": 0}, "size": 0.016579022631049156}, {"text": "approximately", "color": "#00db00", "initloc": {"y": 0, "x": 0}, "size": 0.01659242808818817}, {"text": "derived", "color": "#53ff87", "initloc": {"y": 0, "x": 0}, "size": 0.016743704676628113}, {"text": "include", "color": "#0eff13", "initloc": {"y": 0, "x": 0}, "size": 0.017087236046791077}, {"text": "containing", "color": "#16ff29", "initloc": {"y": 0, "x": 0}, "size": 0.01719028688967228}, {"text": "contains", "color": "#0eff51", "initloc": {"y": 0, "x": 0}, "size": 0.017854927107691765}], "ctm_idx": 121960, "freesurfer_idx": 219553, "hemi": "right"}