{"accuracy": 0.032436228842956535, "rgb": "#8c5584", "cb": 0, "words": [{"text": "abusive", "color": "#ff20b3", "initloc": {"y": 0, "x": 0}, "size": 0.005662976298481226}, {"text": "judge", "color": "#ff408c", "initloc": {"y": 0, "x": 0}, "size": 0.005670940037816763}, {"text": "answering", "color": "#d100ca", "initloc": {"y": 0, "x": 0}, "size": 0.005673063453286886}, {"text": "regret", "color": "#fe00ff", "initloc": {"y": 0, "x": 0}, "size": 0.005680227652192116}, {"text": "apologize", "color": "#ff00f7", "initloc": {"y": 0, "x": 0}, "size": 0.005688758566975594}, {"text": "owe", "color": "#f02973", "initloc": {"y": 0, "x": 0}, "size": 0.005720154382288456}, {"text": "marry", "color": "#ff0c7c", "initloc": {"y": 0, "x": 0}, "size": 0.005751653574407101}, {"text": "selfish", "color": "#ff1cef", "initloc": {"y": 0, "x": 0}, "size": 0.005788243375718594}, {"text": "guilt", "color": "#ff00ed", "initloc": {"y": 0, "x": 0}, "size": 0.005789119750261307}, {"text": "deserved", "color": "#ff4bdc", "initloc": {"y": 0, "x": 0}, "size": 0.005818051286041737}, {"text": "guilty", "color": "#ff16af", "initloc": {"y": 0, "x": 0}, "size": 0.005820850841701031}, {"text": "job", "color": "#bc013d", "initloc": {"y": 0, "x": 0}, "size": 0.005830003414303064}, {"text": "asking", "color": "#fe0097", "initloc": {"y": 0, "x": 0}, "size": 0.005849873647093773}, {"text": "honest", "color": "#ff2dff", "initloc": {"y": 0, "x": 0}, "size": 0.005851391702890396}, {"text": "paying", "color": "#cb1406", "initloc": {"y": 0, "x": 0}, "size": 0.005855952389538288}, {"text": "situation", "color": "#ff00d0", "initloc": {"y": 0, "x": 0}, "size": 0.00590174924582243}, {"text": "deserves", "color": "#ff6af7", "initloc": {"y": 0, "x": 0}, "size": 0.005914020352065563}, {"text": "marriage", "color": "#ff0575", "initloc": {"y": 0, "x": 0}, "size": 0.0059823570773005486}, {"text": "lawyer", "color": "#ff0b50", "initloc": {"y": 0, "x": 0}, "size": 0.006177959032356739}, {"text": "divorce", "color": "#ff0066", "initloc": {"y": 0, "x": 0}, "size": 0.006209870800375938}], "ctm_idx": 7587, "freesurfer_idx": 179456, "hemi": "right"}