{"accuracy": 0.009295700377781685, "rgb": "#7d7485", "cb": 0, "words": [{"text": "dad's", "color": "#fb125f", "initloc": {"y": 0, "x": 0}, "size": 0.0017575144302099943}, {"text": "ride", "color": "#292225", "initloc": {"y": 0, "x": 0}, "size": 0.001758140278980136}, {"text": "birthday", "color": "#da0028", "initloc": {"y": 0, "x": 0}, "size": 0.0017648970242589712}, {"text": "wedding", "color": "#f12613", "initloc": {"y": 0, "x": 0}, "size": 0.001775421667844057}, {"text": "amy", "color": "#ff4689", "initloc": {"y": 0, "x": 0}, "size": 0.0017944378778338432}, {"text": "asks", "color": "#ff0070", "initloc": {"y": 0, "x": 0}, "size": 0.0018509321380406618}, {"text": "doll", "color": "#bae55c", "initloc": {"y": 0, "x": 0}, "size": 0.0018570515094324946}, {"text": "carrie", "color": "#e3444d", "initloc": {"y": 0, "x": 0}, "size": 0.0018759833183139563}, {"text": "kate", "color": "#f34866", "initloc": {"y": 0, "x": 0}, "size": 0.0019057422177866101}, {"text": "sister's", "color": "#ff144f", "initloc": {"y": 0, "x": 0}, "size": 0.0019132345914840698}, {"text": "driver", "color": "#a05000", "initloc": {"y": 0, "x": 0}, "size": 0.0019148210994899273}, {"text": "girl", "color": "#ff4675", "initloc": {"y": 0, "x": 0}, "size": 0.0019206131109967828}, {"text": "friend's", "color": "#e1002a", "initloc": {"y": 0, "x": 0}, "size": 0.0019407784566283226}, {"text": "tells", "color": "#ff00ab", "initloc": {"y": 0, "x": 0}, "size": 0.0019568016286939383}, {"text": "waiting", "color": "#7d0049", "initloc": {"y": 0, "x": 0}, "size": 0.0019579879008233547}, {"text": "boyfriend", "color": "#ff0079", "initloc": {"y": 0, "x": 0}, "size": 0.0019594011828303337}, {"text": "girlfriend", "color": "#ff006b", "initloc": {"y": 0, "x": 0}, "size": 0.0019750227220356464}, {"text": "motorcycle", "color": "#42b200", "initloc": {"y": 0, "x": 0}, "size": 0.002006704453378916}, {"text": "goodbye", "color": "#cc00c8", "initloc": {"y": 0, "x": 0}, "size": 0.0020322527270764112}, {"text": "car", "color": "#683b00", "initloc": {"y": 0, "x": 0}, "size": 0.0021978537552058697}], "ctm_idx": 150660, "freesurfer_idx": 223876, "hemi": "right"}