{"accuracy": 0.016724813193917717, "rgb": "#45c8b5", "cb": 0, "words": [{"text": "river", "color": "#03d229", "initloc": {"y": 0, "x": 0}, "size": 0.019945111125707626}, {"text": "derived", "color": "#53ff87", "initloc": {"y": 0, "x": 0}, "size": 0.02002723515033722}, {"text": "regions", "color": "#00f050", "initloc": {"y": 0, "x": 0}, "size": 0.020064352080225945}, {"text": "its", "color": "#14e75b", "initloc": {"y": 0, "x": 0}, "size": 0.02020336501300335}, {"text": "ocean", "color": "#00af8e", "initloc": {"y": 0, "x": 0}, "size": 0.020248398184776306}, {"text": "outer", "color": "#00ff5f", "initloc": {"y": 0, "x": 0}, "size": 0.02037111297249794}, {"text": "waters", "color": "#00ae9f", "initloc": {"y": 0, "x": 0}, "size": 0.020386800169944763}, {"text": "forming", "color": "#00ff83", "initloc": {"y": 0, "x": 0}, "size": 0.020468134433031082}, {"text": "resulting", "color": "#3dff62", "initloc": {"y": 0, "x": 0}, "size": 0.02048243209719658}, {"text": "diameter", "color": "#00ff40", "initloc": {"y": 0, "x": 0}, "size": 0.020691663026809692}, {"text": "form", "color": "#2dff72", "initloc": {"y": 0, "x": 0}, "size": 0.020694967359304428}, {"text": "vegetation", "color": "#00ff69", "initloc": {"y": 0, "x": 0}, "size": 0.02074250392615795}, {"text": "basin", "color": "#00ee2f", "initloc": {"y": 0, "x": 0}, "size": 0.021024955436587334}, {"text": "forms", "color": "#0eff8d", "initloc": {"y": 0, "x": 0}, "size": 0.021031077951192856}, {"text": "contains", "color": "#0eff51", "initloc": {"y": 0, "x": 0}, "size": 0.021136749535799026}, {"text": "containing", "color": "#16ff29", "initloc": {"y": 0, "x": 0}, "size": 0.021507011726498604}, {"text": "large", "color": "#00ff00", "initloc": {"y": 0, "x": 0}, "size": 0.021678311750292778}, {"text": "surrounding", "color": "#00cb70", "initloc": {"y": 0, "x": 0}, "size": 0.0218509491533041}, {"text": "surface", "color": "#00ff93", "initloc": {"y": 0, "x": 0}, "size": 0.02276114746928215}, {"text": "sea", "color": "#12c161", "initloc": {"y": 0, "x": 0}, "size": 0.02324713207781315}], "ctm_idx": 83544, "freesurfer_idx": 302045, "hemi": "right"}