{"accuracy": 0.0717764867454586, "rgb": "#71d27a", "cb": 1, "words": [{"text": "designed", "color": "#00ff2d", "initloc": {"y": 0, "x": 0}, "size": 0.014572733081877232}, {"text": "g", "color": "#30ff43", "initloc": {"y": 0, "x": 0}, "size": 0.014717452228069305}, {"text": "using", "color": "#2de8a1", "initloc": {"y": 0, "x": 0}, "size": 0.014759602025151253}, {"text": "string", "color": "#30f573", "initloc": {"y": 0, "x": 0}, "size": 0.014836982823908329}, {"text": "additional", "color": "#00c500", "initloc": {"y": 0, "x": 0}, "size": 0.01493446622043848}, {"text": "standard", "color": "#10f621", "initloc": {"y": 0, "x": 0}, "size": 0.01496630534529686}, {"text": "inserted", "color": "#74ff68", "initloc": {"y": 0, "x": 0}, "size": 0.014993305318057537}, {"text": "containing", "color": "#16ff29", "initloc": {"y": 0, "x": 0}, "size": 0.015063147060573101}, {"text": "technique", "color": "#00ffd0", "initloc": {"y": 0, "x": 0}, "size": 0.01508311927318573}, {"text": "frames", "color": "#00ff36", "initloc": {"y": 0, "x": 0}, "size": 0.015099220909178257}, {"text": "vertical", "color": "#00ff44", "initloc": {"y": 0, "x": 0}, "size": 0.015111545100808144}, {"text": "designs", "color": "#00ff1b", "initloc": {"y": 0, "x": 0}, "size": 0.015186956152319908}, {"text": "method", "color": "#2fe7a8", "initloc": {"y": 0, "x": 0}, "size": 0.015818865969777107}, {"text": "adding", "color": "#18efbf", "initloc": {"y": 0, "x": 0}, "size": 0.015946367755532265}, {"text": "cylinder", "color": "#00ff22", "initloc": {"y": 0, "x": 0}, "size": 0.016026105731725693}, {"text": "design", "color": "#00e045", "initloc": {"y": 0, "x": 0}, "size": 0.016075080260634422}, {"text": "uses", "color": "#48ff9f", "initloc": {"y": 0, "x": 0}, "size": 0.016255320981144905}, {"text": "x", "color": "#1bce37", "initloc": {"y": 0, "x": 0}, "size": 0.01691925711929798}, {"text": "added", "color": "#00e945", "initloc": {"y": 0, "x": 0}, "size": 0.017506875097751617}, {"text": "modified", "color": "#26ff56", "initloc": {"y": 0, "x": 0}, "size": 0.017869599163532257}], "ctm_idx": 124444, "freesurfer_idx": 9528, "hemi": "left"}