{"accuracy": 0.0489650186550167, "rgb": "#73c8bd", "cb": 0, "words": [{"text": "shapes", "color": "#00ffc9", "initloc": {"y": 0, "x": 0}, "size": 0.009095467627048492}, {"text": "wax", "color": "#24ff99", "initloc": {"y": 0, "x": 0}, "size": 0.009109788574278355}, {"text": "combination", "color": "#02ffaa", "initloc": {"y": 0, "x": 0}, "size": 0.009188209660351276}, {"text": "powder", "color": "#18ff82", "initloc": {"y": 0, "x": 0}, "size": 0.009207856841385365}, {"text": "type", "color": "#51ffa4", "initloc": {"y": 0, "x": 0}, "size": 0.009227750822901726}, {"text": "shape", "color": "#00ffa6", "initloc": {"y": 0, "x": 0}, "size": 0.009235001169145107}, {"text": "remove", "color": "#8dfd85", "initloc": {"y": 0, "x": 0}, "size": 0.009237509220838547}, {"text": "add", "color": "#3fdf9b", "initloc": {"y": 0, "x": 0}, "size": 0.00924057886004448}, {"text": "thicker", "color": "#05ffb9", "initloc": {"y": 0, "x": 0}, "size": 0.009257154539227486}, {"text": "pinch", "color": "#54ff94", "initloc": {"y": 0, "x": 0}, "size": 0.009321621619164944}, {"text": "pieces", "color": "#02ff5d", "initloc": {"y": 0, "x": 0}, "size": 0.009539010003209114}, {"text": "blade", "color": "#39ff9f", "initloc": {"y": 0, "x": 0}, "size": 0.009753454476594925}, {"text": "seal", "color": "#66ff5e", "initloc": {"y": 0, "x": 0}, "size": 0.009776927530765533}, {"text": "using", "color": "#2de8a1", "initloc": {"y": 0, "x": 0}, "size": 0.009786805137991905}, {"text": "inserted", "color": "#74ff68", "initloc": {"y": 0, "x": 0}, "size": 0.009972616098821163}, {"text": "plastic", "color": "#06ff46", "initloc": {"y": 0, "x": 0}, "size": 0.00998844113200903}, {"text": "uses", "color": "#48ff9f", "initloc": {"y": 0, "x": 0}, "size": 0.010015062056481838}, {"text": "metal", "color": "#00ff82", "initloc": {"y": 0, "x": 0}, "size": 0.010068537667393684}, {"text": "bottom", "color": "#00ff30", "initloc": {"y": 0, "x": 0}, "size": 0.010094575583934784}, {"text": "piece", "color": "#2fff7e", "initloc": {"y": 0, "x": 0}, "size": 0.010205727070569992}], "ctm_idx": 97913, "freesurfer_idx": 316551, "hemi": "right"}