{"accuracy": 0.012012269628523123, "rgb": "#6d8d8b", "cb": 0, "words": [{"text": "hull", "color": "#10e21f", "initloc": {"y": 0, "x": 0}, "size": 0.003969151061028242}, {"text": "meters", "color": "#00fd1f", "initloc": {"y": 0, "x": 0}, "size": 0.003973012790083885}, {"text": "vessel", "color": "#44c352", "initloc": {"y": 0, "x": 0}, "size": 0.003984001465141773}, {"text": "m", "color": "#00d700", "initloc": {"y": 0, "x": 0}, "size": 0.003987235017120838}, {"text": "reaches", "color": "#0bf76b", "initloc": {"y": 0, "x": 0}, "size": 0.003998954314738512}, {"text": "addition", "color": "#00e100", "initloc": {"y": 0, "x": 0}, "size": 0.004001943860203028}, {"text": "reaching", "color": "#00e058", "initloc": {"y": 0, "x": 0}, "size": 0.004003000445663929}, {"text": "eastward", "color": "#117c33", "initloc": {"y": 0, "x": 0}, "size": 0.004006457049399614}, {"text": "ocean", "color": "#00af8e", "initloc": {"y": 0, "x": 0}, "size": 0.004009018186479807}, {"text": "basin", "color": "#00ee2f", "initloc": {"y": 0, "x": 0}, "size": 0.004044197499752045}, {"text": "air", "color": "#00dc64", "initloc": {"y": 0, "x": 0}, "size": 0.004083580337464809}, {"text": "rapidly", "color": "#07e791", "initloc": {"y": 0, "x": 0}, "size": 0.004089098423719406}, {"text": "placed", "color": "#48e600", "initloc": {"y": 0, "x": 0}, "size": 0.00409415178000927}, {"text": "forming", "color": "#00ff83", "initloc": {"y": 0, "x": 0}, "size": 0.004138002172112465}, {"text": "formation", "color": "#00f667", "initloc": {"y": 0, "x": 0}, "size": 0.004158698488026857}, {"text": "steel", "color": "#00ff39", "initloc": {"y": 0, "x": 0}, "size": 0.004251678474247456}, {"text": "formed", "color": "#10ed49", "initloc": {"y": 0, "x": 0}, "size": 0.004302868619561195}, {"text": "surface", "color": "#00ff93", "initloc": {"y": 0, "x": 0}, "size": 0.004502380266785622}, {"text": "resulting", "color": "#3dff62", "initloc": {"y": 0, "x": 0}, "size": 0.004503114148974419}, {"text": "sea", "color": "#12c161", "initloc": {"y": 0, "x": 0}, "size": 0.0045873369090259075}], "ctm_idx": 111398, "freesurfer_idx": 267278, "hemi": "right"}