{"accuracy": 0.022875543348359027, "rgb": "#558a6b", "cb": 0, "words": [{"text": "slopes", "color": "#00f449", "initloc": {"y": 0, "x": 0}, "size": 0.012357590720057487}, {"text": "miles", "color": "#01740c", "initloc": {"y": 0, "x": 0}, "size": 0.01237720437347889}, {"text": "wooded", "color": "#00ab1e", "initloc": {"y": 0, "x": 0}, "size": 0.0123977055773139}, {"text": "located", "color": "#00a200", "initloc": {"y": 0, "x": 0}, "size": 0.012479563243687153}, {"text": "bridge", "color": "#00b021", "initloc": {"y": 0, "x": 0}, "size": 0.012575355358421803}, {"text": "kilometers", "color": "#00a824", "initloc": {"y": 0, "x": 0}, "size": 0.01258929818868637}, {"text": "steep", "color": "#00ba4e", "initloc": {"y": 0, "x": 0}, "size": 0.012590830214321613}, {"text": "inland", "color": "#0ba63f", "initloc": {"y": 0, "x": 0}, "size": 0.012818683870136738}, {"text": "basin", "color": "#00ee2f", "initloc": {"y": 0, "x": 0}, "size": 0.012825088575482368}, {"text": "bay", "color": "#009121", "initloc": {"y": 0, "x": 0}, "size": 0.012868941761553288}, {"text": "adjacent", "color": "#009700", "initloc": {"y": 0, "x": 0}, "size": 0.012887047603726387}, {"text": "kilometres", "color": "#05a90e", "initloc": {"y": 0, "x": 0}, "size": 0.012967697344720364}, {"text": "area", "color": "#00a800", "initloc": {"y": 0, "x": 0}, "size": 0.013019049540162086}, {"text": "river", "color": "#03d229", "initloc": {"y": 0, "x": 0}, "size": 0.013048983179032803}, {"text": "tunnels", "color": "#008f68", "initloc": {"y": 0, "x": 0}, "size": 0.013127805665135384}, {"text": "boats", "color": "#00920f", "initloc": {"y": 0, "x": 0}, "size": 0.01318212877959013}, {"text": "metres", "color": "#00e206", "initloc": {"y": 0, "x": 0}, "size": 0.013183891773223877}, {"text": "ocean", "color": "#00af8e", "initloc": {"y": 0, "x": 0}, "size": 0.01334158331155777}, {"text": "nearby", "color": "#175c00", "initloc": {"y": 0, "x": 0}, "size": 0.013412782922387123}, {"text": "meters", "color": "#00fd1f", "initloc": {"y": 0, "x": 0}, "size": 0.014308469370007515}], "ctm_idx": 112533, "freesurfer_idx": 187541, "hemi": "right"}