{"accuracy": 0.012432733293873814, "rgb": "#756d6f", "cb": 0, "words": [{"text": "operated", "color": "#0a9500", "initloc": {"y": 0, "x": 0}, "size": 0.004963961895555258}, {"text": "suburban", "color": "#2b6f08", "initloc": {"y": 0, "x": 0}, "size": 0.004976164549589157}, {"text": "stations", "color": "#00800a", "initloc": {"y": 0, "x": 0}, "size": 0.004984525963664055}, {"text": "hampshire", "color": "#6b7500", "initloc": {"y": 0, "x": 0}, "size": 0.004997214302420616}, {"text": "railway", "color": "#127d00", "initloc": {"y": 0, "x": 0}, "size": 0.005000053904950619}, {"text": "district", "color": "#588a00", "initloc": {"y": 0, "x": 0}, "size": 0.005001146346330643}, {"text": "boston", "color": "#406e00", "initloc": {"y": 0, "x": 0}, "size": 0.005008676089346409}, {"text": "baltimore", "color": "#4d7200", "initloc": {"y": 0, "x": 0}, "size": 0.005033400841057301}, {"text": "trains", "color": "#005a03", "initloc": {"y": 0, "x": 0}, "size": 0.005043758079409599}, {"text": "offices", "color": "#253e00", "initloc": {"y": 0, "x": 0}, "size": 0.005053927190601826}, {"text": "city's", "color": "#219100", "initloc": {"y": 0, "x": 0}, "size": 0.005116885062307119}, {"text": "ferry", "color": "#156200", "initloc": {"y": 0, "x": 0}, "size": 0.005131865851581097}, {"text": "boulevard", "color": "#007800", "initloc": {"y": 0, "x": 0}, "size": 0.005133522674441338}, {"text": "station", "color": "#005a00", "initloc": {"y": 0, "x": 0}, "size": 0.005157755687832832}, {"text": "airport", "color": "#221e00", "initloc": {"y": 0, "x": 0}, "size": 0.005162893794476986}, {"text": "plaza", "color": "#006900", "initloc": {"y": 0, "x": 0}, "size": 0.00519227609038353}, {"text": "headquarters", "color": "#475900", "initloc": {"y": 0, "x": 0}, "size": 0.005300331395119429}, {"text": "downtown", "color": "#004d00", "initloc": {"y": 0, "x": 0}, "size": 0.005365805700421333}, {"text": "avenue", "color": "#006600", "initloc": {"y": 0, "x": 0}, "size": 0.005421547219157219}, {"text": "campus", "color": "#001d00", "initloc": {"y": 0, "x": 0}, "size": 0.00542211439460516}], "ctm_idx": 144571, "freesurfer_idx": 72430, "hemi": "left"}